graphbutler.py
graphbutler-0.2.0.dist-info/DESCRIPTION.rst
graphbutler-0.2.0.dist-info/METADATA
graphbutler-0.2.0.dist-info/RECORD
graphbutler-0.2.0.dist-info/WHEEL
graphbutler-0.2.0.dist-info/metadata.json
graphbutler-0.2.0.dist-info/top_level.txt
